firstock/__init__.py
firstock/firstock.py
firstock/Variables/__init__.py
firstock/Variables/common_imports.py
firstock/Variables/enums.py
firstock/Variables/error_list.py
firstock/Variables/fixedParams.py
firstock/commonImports/__init__.py
firstock/commonImports/importers.py
firstock/loginNProfile/__init__.py
firstock/loginNProfile/loginFirstock.py
firstock/loginNProfile/logoutFirstock.py
firstock/loginNProfile/userDetailsFirstock.py
firstock/loginNProfile/loginFunctionality/__init__.py
firstock/loginNProfile/loginFunctionality/base.py
firstock/loginNProfile/loginFunctionality/execution.py
firstock/loginNProfile/loginFunctionality/functions.py
firstock/loginNProfile/logoutFunctionality/__init__.py
firstock/loginNProfile/logoutFunctionality/base.py
firstock/loginNProfile/logoutFunctionality/execution.py
firstock/loginNProfile/logoutFunctionality/functions.py
firstock/loginNProfile/userDetailsFunctionality/__init__.py
firstock/loginNProfile/userDetailsFunctionality/base.py
firstock/loginNProfile/userDetailsFunctionality/execution.py
firstock/loginNProfile/userDetailsFunctionality/functions.py
firstock/marketConnect/__init__.py
firstock/marketConnect/brokerageCalculatorFirstock.py
firstock/marketConnect/expiryFirstock.py
firstock/marketConnect/getIndexListFirstock.py
firstock/marketConnect/getMultiQuoteFirstock.py
firstock/marketConnect/getMultiQuoteLTPFirstock.py
firstock/marketConnect/getOptionChainFirstock.py
firstock/marketConnect/getQuoteLTPFirstock.py
firstock/marketConnect/getQuotesFirstock.py
firstock/marketConnect/getSecurityInfoFirstock.py
firstock/marketConnect/searchScripsFirstock.py
firstock/marketConnect/timePriceSeriesFirstock.py
firstock/marketConnect/brokerageCalculatorFunctionality/__init__.py
firstock/marketConnect/brokerageCalculatorFunctionality/base.py
firstock/marketConnect/brokerageCalculatorFunctionality/execution.py
firstock/marketConnect/brokerageCalculatorFunctionality/functions.py
firstock/marketConnect/getExpiryFunctionality/__init__.py
firstock-1.1.1.dist-info/METADATA
firstock-1.1.1.dist-info/WHEEL
firstock-1.1.1.dist-info/licenses/LICENSE
firstock-1.1.1.dist-info/RECORD
