Metadata-Version: 2.4
Name: firstock
Version: 1.1.1
Summary: Firstock Developer SDK for Python
Project-URL: Homepage, https://github.com/the-firstock/firstock-developer-sdk-python
Author-email: Firstock <technology@thefirstock.com>
License-File: LICENSE
Classifier: Intended Audience :: Developers
Classifier: License :: OSI Approved :: MIT License
Classifier: Operating System :: OS Independent
Classifier: Programming Language :: Python :: 3
Classifier: Topic :: Software Development :: Libraries :: Python Modules
Requires-Python: >=3.7
Requires-Dist: requests>=2.25.0
Requires-Dist: websocket-client>=1.0.0
